<?xml version="1.0" encoding="euc-kr" ?> 
<MainGame>
<Screen>
	<Size w="800" h="600"></Size>
</Screen>
<MainPanel>
	<Bg> </Bg>
	<Enemy>
		<Obj x="370" y="60" w="62" h="75" img="image/enemy1.png"></Obj>

	</Enemy>
	<Meteor>
		<Obj x="336" y="143" w="33" h="40" life = "1" speed = "7" img="image/meteo1.png"></Obj>
		<Obj x="475" y="203" w="33" h="40" life = "1" speed = "7" img="image/meteo1.png"></Obj>
		<Obj x="305" y="275" w="33" h="40" life = "1" speed = "7" img="image/meteo1.png"></Obj>
		<Obj x="350" y="328" w="33" h="40" life = "1" speed = "7" img="image/meteo1.png"></Obj>
		<Obj x="430" y="328" w="33" h="40" life = "1" speed = "7" img="image/meteo1.png"></Obj>
		<Obj x="505" y="275" w="33" h="40" life = "1" speed = "7" img="image/meteo1.png"></Obj>
		<Obj x="441" y="143" w="40" h="38" life = "2" speed = "7" img="image/meteo2.png"></Obj>
		<Obj x="285" y="203" w="40" h="38" life = "2" speed = "7" img="image/meteo2.png"></Obj>
	</Meteor>
	<Player>
		<Obj x="400" y="460" w="40" h="60" img="image/spaceship_small.png"></Obj>
	</Player>
</MainPanel>
</MainGame>